memview/__init__.py
memview/cli.py
memview/errors.py
memview/layout.py
memview/loaders.py
memview/memory.py
memview/reporters.py
memview-0.1.3.dist-info/licenses/LICENSE
memview-0.1.3.dist-info/METADATA
memview-0.1.3.dist-info/WHEEL
memview-0.1.3.dist-info/entry_points.txt
memview-0.1.3.dist-info/top_level.txt
memview-0.1.3.dist-info/RECORD
