Metadata-Version: 2.4
Name: memview
Version: 0.1.3
Summary: Introspect and visualize binary memory layouts
Author-email: "Ioannis D (devcoons)" <support@devcoons.com>
License-Expression: MIT
Project-URL: Homepage, https://github.com/devcoons/memview
Project-URL: Issues, https://github.com/devcoons/memview/issues
Keywords: memview,firmware,binary,intel-hex,srec
Classifier: Development Status :: 5 - Production/Stable
Classifier: Intended Audience :: Developers
Classifier: Natural Language :: English
Classifier: Operating System :: OS Independent
Classifier: Programming Language :: Python :: 3 :: Only
Classifier: Programming Language :: Python :: 3.11
Classifier: Programming Language :: Python :: 3.12
Classifier: Programming Language :: Python :: 3.13
Classifier: Programming Language :: Python :: 3.14
Classifier: Programming Language :: Python :: Implementation :: CPython
Classifier: Programming Language :: Python :: Implementation :: PyPy
Requires-Python: >=3.11
License-File: LICENSE
Requires-Dist: ihexsrec>=0.1.0
Provides-Extra: yaml
Requires-Dist: PyYAML>=6.0; extra == "yaml"
Provides-Extra: svg
Requires-Dist: svgwrite>=1.4; extra == "svg"
Provides-Extra: elf
Requires-Dist: pyelftools>=0.30; extra == "elf"
Provides-Extra: hash
Requires-Dist: xxhash>=3.4; extra == "hash"
Provides-Extra: speed
Requires-Dist: sortedcontainers>=2.4; extra == "speed"
Provides-Extra: dev
Requires-Dist: pytest>=8; extra == "dev"
Requires-Dist: mypy>=1.10; extra == "dev"
Requires-Dist: ruff>=0.5; extra == "dev"
Requires-Dist: pip-tools>=7; extra == "dev"
Dynamic: license-file
